odoo8_addon_procurement_jit_assign_move-8.0.1.0.0.99.dev12-nspkg.pth
odoo_addons/procurement_jit_assign_move/README.rst
odoo_addons/procurement_jit_assign_move/__init__.py
odoo_addons/procurement_jit_assign_move/__openerp__.py
odoo_addons/procurement_jit_assign_move/i18n/ca.po
odoo_addons/procurement_jit_assign_move/i18n/de.po
odoo_addons/procurement_jit_assign_move/i18n/es.po
odoo_addons/procurement_jit_assign_move/i18n/es_AR.po
odoo_addons/procurement_jit_assign_move/i18n/es_MX.po
odoo_addons/procurement_jit_assign_move/i18n/fi.po
odoo_addons/procurement_jit_assign_move/i18n/fr.po
odoo_addons/procurement_jit_assign_move/i18n/hr.po
odoo_addons/procurement_jit_assign_move/i18n/it.po
odoo_addons/procurement_jit_assign_move/i18n/procurement_jit_assign_move.pot
odoo_addons/procurement_jit_assign_move/i18n/pt.po
odoo_addons/procurement_jit_assign_move/i18n/pt_BR.po
odoo_addons/procurement_jit_assign_move/i18n/sl.po
odoo_addons/procurement_jit_assign_move/i18n/tr.po
odoo_addons/procurement_jit_assign_move/i18n/tr_TR.po
odoo_addons/procurement_jit_assign_move/models/__init__.py
odoo_addons/procurement_jit_assign_move/models/stock_move.py
odoo_addons/procurement_jit_assign_move/static/description/icon.png
odoo_addons/procurement_jit_assign_move/tests/__init__.py
odoo_addons/procurement_jit_assign_move/tests/test_procurement.py
odoo8_addon_procurement_jit_assign_move-8.0.1.0.0.99.dev12.dist-info/METADATA
odoo8_addon_procurement_jit_assign_move-8.0.1.0.0.99.dev12.dist-info/WHEEL
odoo8_addon_procurement_jit_assign_move-8.0.1.0.0.99.dev12.dist-info/namespace_packages.txt
odoo8_addon_procurement_jit_assign_move-8.0.1.0.0.99.dev12.dist-info/top_level.txt
odoo8_addon_procurement_jit_assign_move-8.0.1.0.0.99.dev12.dist-info/RECORD
